eternal_math/__init__.py
eternal_math/cli.py
eternal_math/core.py
eternal_math/number_theory.py
eternal_math/proofs.py
eternal_math/symbolic.py
eternal_math/visualization.py
eternal_math-0.1.0.dist-info/METADATA
eternal_math-0.1.0.dist-info/WHEEL
eternal_math-0.1.0.dist-info/entry_points.txt
eternal_math-0.1.0.dist-info/licenses/LICENSE
eternal_math-0.1.0.dist-info/RECORD
