Metadata-Version: 2.4
Name: eternal-math
Version: 0.1.0
Summary: An open-source software platform for exploring, proving, and generating mathematical concepts
Project-URL: Homepage, https://github.com/Vooblin/eternal-math
Project-URL: Bug Reports, https://github.com/Vooblin/eternal-math/issues
Project-URL: Source, https://github.com/Vooblin/eternal-math
Author-email: Dmitrii Murygin <dmitrij.murygin7@gmail.com>
License-Expression: MIT
License-File: LICENSE
Keywords: mathematics,number-theory,proofs,symbolic-math,visualization
Classifier: Development Status :: 3 - Alpha
Classifier: Intended Audience :: Science/Research
Classifier: License :: OSI Approved :: MIT License
Classifier: Programming Language :: Python :: 3
Classifier: Programming Language :: Python :: 3.12
Classifier: Topic :: Scientific/Engineering :: Mathematics
Requires-Python: >=3.12
Requires-Dist: matplotlib>=3.5.0
Requires-Dist: numpy>=1.21.0
Requires-Dist: sympy>=1.9
Provides-Extra: dev
Requires-Dist: black; extra == 'dev'
Requires-Dist: flake8; extra == 'dev'
Requires-Dist: isort; extra == 'dev'
Requires-Dist: pytest-cov; extra == 'dev'
Requires-Dist: pytest>=6.0; extra == 'dev'
